LICENSE.txt
README.md
setup.py
rocketo/__init__.py
rocketo/rocketo.py
rocketo.egg-info/PKG-INFO
rocketo.egg-info/SOURCES.txt
rocketo.egg-info/dependency_links.txt
rocketo.egg-info/requires.txt
rocketo.egg-info/top_level.txt