Metadata-Version: 2.1
Name: rocketo
Version: 1.0.0
Summary: An awesome package that does something
Home-page: http://pypi.python.org/pypi/rocketo/
Author: Larbi
Author-email: larbiachraf03@gmail.com
License: LICENSE.txt
License-File: LICENSE.txt
Requires-Dist: rocketo
